auth_helper.py
auth_mcp_stdio.py
auth_mcp_stdio_v2.py
teamcenter_mcp_server-0.2.2.dist-info/METADATA
teamcenter_mcp_server-0.2.2.dist-info/WHEEL
teamcenter_mcp_server-0.2.2.dist-info/entry_points.txt
teamcenter_mcp_server-0.2.2.dist-info/top_level.txt
teamcenter_mcp_server-0.2.2.dist-info/RECORD
