Metadata-Version: 2.4
Name: teamcenter-mcp-server
Version: 0.2.2
Summary: MCP server for Teamcenter Knowledge Base with Azure AD and cookie authentication
Author: Siemens Digital Industries Software
License: MIT
Project-URL: Homepage, https://github.com/siemens/teamcenter-mcp-server
Project-URL: Bug Reports, https://github.com/siemens/teamcenter-mcp-server/issues
Project-URL: Documentation, https://github.com/siemens/teamcenter-mcp-server#readme
Keywords: mcp,teamcenter,siemens,ai,llm
Classifier: Development Status :: 4 - Beta
Classifier: Intended Audience :: Developers
Classifier: License :: OSI Approved :: MIT License
Classifier: Programming Language :: Python :: 3
Classifier: Programming Language :: Python :: 3.10
Classifier: Programming Language :: Python :: 3.11
Classifier: Programming Language :: Python :: 3.12
Requires-Python: >=3.10
Requires-Dist: fastapi>=0.104.1
Requires-Dist: uvicorn>=0.24.0
Requires-Dist: fastmcp>=0.1.0
Requires-Dist: httpx>=0.24.0
Requires-Dist: requests>=2.28.0
Requires-Dist: msal>=1.20.0
Provides-Extra: dev
Requires-Dist: pytest>=7.0.0; extra == "dev"
Requires-Dist: pytest-asyncio>=0.21.0; extra == "dev"
